mcp_chat/__init__.py
mcp_chat/cli_chat.py
mcp_chat/config_loader.py
mcp_chat-0.2.14.dist-info/METADATA
mcp_chat-0.2.14.dist-info/WHEEL
mcp_chat-0.2.14.dist-info/entry_points.txt
mcp_chat-0.2.14.dist-info/licenses/LICENSE
mcp_chat-0.2.14.dist-info/RECORD
