Metadata-Version: 2.4
Name: mcp-chat
Version: 0.2.14
Summary: Simple MCP Client to quickly test and explore MCP servers from the command line
Project-URL: Bug Tracker, https://github.com/hideya/mcp-client-langchain-py/issues
Project-URL: Source Code, https://github.com/hideya/mcp-client-langchain-py
License-File: LICENSE
Keywords: cli,client,explore,langchain,mcp,model-context-protocol,python,quick,simple,test,tools,try
Requires-Python: >=3.11
Requires-Dist: langchain-anthropic>=0.3.1
Requires-Dist: langchain-cerebras>=0.5.0
Requires-Dist: langchain-google-genai>=2.1.5
Requires-Dist: langchain-groq>=0.3.7
Requires-Dist: langchain-mcp-tools>=0.2.12
Requires-Dist: langchain-openai>=0.3.0
Requires-Dist: langchain-xai>=0.2.4
Requires-Dist: langchain>=0.3.26
Requires-Dist: langgraph>=0.5.0
Requires-Dist: pyjson5>=1.6.8
Requires-Dist: python-dotenv>=1.0.1
Requires-Dist: websockets>=15.0.1
